proksee_batch/__init__.py
proksee_batch/__main__.py
proksee_batch/data/assets/images/GitHub-Mark-Light-64px.png
proksee_batch/data/assets/scripts/batch.js
proksee_batch/data/assets/scripts/cgview.min.js
proksee_batch/data/assets/scripts/controls.js
proksee_batch/data/assets/scripts/d3.min.js
proksee_batch/data/assets/scripts/svgcanvas.iife.js
proksee_batch/data/assets/styles/cgview.css
proksee_batch/data/assets/styles/controls.css
proksee_batch/data/assets/styles/style.css
proksee_batch/data/data.example/genome_maps/genome_1.js
proksee_batch/data/data.example/genome_maps/genome_2.js
proksee_batch/data/data.example/genome_maps/genome_3.js
proksee_batch/data/data.example/genome_maps/genome_4.js
proksee_batch/data/data.example/table_data.js
proksee_batch/data/default_proksee_template.json
proksee_batch/data/example_input_dir/Escherichia_coli_str._K-12_substr._MG1655/bed/e_coli_features.bed
proksee_batch/data/example_input_dir/Escherichia_coli_str._K-12_substr._MG1655/blast/blast_against_e_coli.txt
proksee_batch/data/example_input_dir/Escherichia_coli_str._K-12_substr._MG1655/vcf/e_coli_variants.vcf
proksee_batch/data/example_input_dir/Klebsiella_aerogenes/bed/k_aerogenes_features.bed
proksee_batch/data/example_input_dir/Klebsiella_aerogenes/blast/blast_against_k_aerogenes.txt
proksee_batch/data/example_input_dir/Klebsiella_aerogenes/metadata/example_metadata.json
proksee_batch/data/example_input_dir/Salmonella_enterica_subsp._enterica_serovar_Typhimurium_str._LT2/bed/s_enterica_features.bed
proksee_batch/data/example_input_dir/Salmonella_enterica_subsp._enterica_serovar_Typhimurium_str._LT2/blast/blast_against_s_enterica.txt
proksee_batch/data/example_input_dir/Shigella_flexneri_2a_str._301/bed/s_flexneri_features.bed
proksee_batch/data/example_input_dir/Shigella_flexneri_2a_str._301/blast/blast_against_s_flexneri.txt
proksee_batch/data/report.html
proksee_batch/download_example_input.py
proksee_batch/generate_proksee_link.py
proksee_batch/generate_report_html.py
proksee_batch-0.6.11.dist-info/LICENSE
proksee_batch-0.6.11.dist-info/METADATA
proksee_batch-0.6.11.dist-info/WHEEL
proksee_batch-0.6.11.dist-info/entry_points.txt
proksee_batch-0.6.11.dist-info/RECORD
