Metadata-Version: 2.3
Name: proksee-batch
Version: 0.6.11
Summary: Proksee Batch
License: MIT
Author: Lael D. Barlow
Requires-Python: >=3.13,<3.14
Classifier: Development Status :: 3 - Alpha
Classifier: License :: OSI Approved :: MIT License
Classifier: Programming Language :: Python :: 3
Classifier: Programming Language :: Python :: 3.13
Requires-Dist: biopython (>=1.83)
Requires-Dist: click (>=8.0.1)
Requires-Dist: gffutils (>=0.12,<0.13)
Requires-Dist: poetry-plugin-export (>=1.6.0,<2.0.0)
Requires-Dist: requests (>=2.31.0,<3.0.0)
Requires-Dist: seaborn (>=0.13.2,<0.14.0)
Requires-Dist: selenium (>=4.16.0,<5.0.0)
Requires-Dist: toml (>=0.10.2,<0.11.0)
Requires-Dist: types-requests (>=2.31.0.20240106,<3.0.0.0)
Requires-Dist: types-selenium (>=3.141.9,<4.0.0)
Requires-Dist: types-toml (>=0.10.8.7,<0.11.0.0)
Requires-Dist: webdriver-manager (>=4.0.1,<5.0.0)
Project-URL: Changelog, https://github.com/stothard-group/proksee-batch/releases
Project-URL: Documentation, https://proksee-batch.readthedocs.io
Project-URL: Homepage, https://github.com/stothard-group/proksee-batch
Project-URL: Repository, https://github.com/stothard-group/proksee-batch
